odoo/addons/multicompany_configuration/README.rst
odoo/addons/multicompany_configuration/__init__.py
odoo/addons/multicompany_configuration/__manifest__.py
odoo/addons/multicompany_configuration/i18n/es.po
odoo/addons/multicompany_configuration/i18n/it.po
odoo/addons/multicompany_configuration/i18n/multicompany_configuration.pot
odoo/addons/multicompany_configuration/models/__init__.py
odoo/addons/multicompany_configuration/models/multicompany_abstract.py
odoo/addons/multicompany_configuration/models/product_category.py
odoo/addons/multicompany_configuration/models/product_template.py
odoo/addons/multicompany_configuration/models/res_partner.py
odoo/addons/multicompany_configuration/readme/CONTRIBUTORS.rst
odoo/addons/multicompany_configuration/readme/DESCRIPTION.rst
odoo/addons/multicompany_configuration/static/description/icon.png
odoo/addons/multicompany_configuration/static/description/index.html
odoo/addons/multicompany_configuration/static/src/components/multicompany_data_field/multicompany_data_field.esm.js
odoo/addons/multicompany_configuration/static/src/components/multicompany_data_field/multicompany_data_field.xml
odoo/addons/multicompany_configuration/views/product_category.xml
odoo/addons/multicompany_configuration/views/product_product.xml
odoo/addons/multicompany_configuration/views/product_template.xml
odoo/addons/multicompany_configuration/views/res_partner.xml
odoo_addon_multicompany_configuration-16.0.1.0.0.4.dist-info/METADATA
odoo_addon_multicompany_configuration-16.0.1.0.0.4.dist-info/WHEEL
odoo_addon_multicompany_configuration-16.0.1.0.0.4.dist-info/top_level.txt
odoo_addon_multicompany_configuration-16.0.1.0.0.4.dist-info/RECORD
